[1,["64LamgJ+9M/YeoFuDIJu87@6c48a"],["_textureSource"],["cc.SpriteFrame","cc.SpriteAtlas"],0,[[[{"name":"type_0","spriteFrames":["没牛00","63oq8IHANALZbR2UmTHdMb@aad25","没牛01","63oq8IHANALZbR2UmTHdMb@5e923","没牛02","63oq8IHANALZbR2UmTHdMb@65804","没牛03","63oq8IHANALZbR2UmTHdMb@68990","没牛04","63oq8IHANALZbR2UmTHdMb@4bd08","没牛05","63oq8IHANALZbR2UmTHdMb@58e55","没牛06","63oq8IHANALZbR2UmTHdMb@33a0a","没牛07","63oq8IHANALZbR2UmTHdMb@7687f","没牛08","63oq8IHANALZbR2UmTHdMb@708dd","没牛09","63oq8IHANALZbR2UmTHdMb@7fcf7","没牛10","63oq8IHANALZbR2UmTHdMb@8b204","没牛11","63oq8IHANALZbR2UmTHdMb@e324c","没牛12","63oq8IHANALZbR2UmTHdMb@4dbd1"]}],[1],0,[],[],[]],[[{"name":"没牛06","rect":{"x":397,"y":1,"width":196,"height":112},"offset":{"x":0,"y":1},"originalSize":{"width":196,"height":114},"rotated":false,"capInsets":[0,0,0,0],"vertices":{"rawPosition":[],"indexes":[],"uv":[],"nuv":[],"minPos":{"x":0,"y":0,"z":0},"maxPos":{"x":0,"y":0,"z":0}},"packable":true,"pixelsToUnit":100,"pivot":{"x":0.5,"y":0.5},"meshType":0}],[0],0,[0],[0],[0]],[[{"name":"没牛04","rect":{"x":1387,"y":1,"width":196,"height":92},"offset":{"x":0,"y":-11},"originalSize":{"width":196,"height":114},"rotated":false,"capInsets":[0,0,0,0],"vertices":{"rawPosition":[],"indexes":[],"uv":[],"nuv":[],"minPos":{"x":0,"y":0,"z":0},"maxPos":{"x":0,"y":0,"z":0}},"packable":true,"pixelsToUnit":100,"pivot":{"x":0.5,"y":0.5},"meshType":0}],[0],0,[0],[0],[0]],[[{"name":"没牛12","rect":{"x":1,"y":1,"width":196,"height":114},"offset":{"x":0,"y":0},"originalSize":{"width":196,"height":114},"rotated":false,"capInsets":[0,0,0,0],"vertices":{"rawPosition":[],"indexes":[],"uv":[],"nuv":[],"minPos":{"x":0,"y":0,"z":0},"maxPos":{"x":0,"y":0,"z":0}},"packable":true,"pixelsToUnit":100,"pivot":{"x":0.5,"y":0.5},"meshType":0}],[0],0,[0],[0],[0]],[[{"name":"没牛05","rect":{"x":1,"y":1,"width":196,"height":114},"offset":{"x":0,"y":0},"originalSize":{"width":196,"height":114},"rotated":false,"capInsets":[0,0,0,0],"vertices":{"rawPosition":[],"indexes":[],"uv":[],"nuv":[],"minPos":{"x":0,"y":0,"z":0},"maxPos":{"x":0,"y":0,"z":0}},"packable":true,"pixelsToUnit":100,"pivot":{"x":0.5,"y":0.5},"meshType":0}],[0],0,[0],[0],[0]],[[{"name":"没牛01","rect":{"x":1387,"y":95,"width":196,"height":22},"offset":{"x":0,"y":-46},"originalSize":{"width":196,"height":114},"rotated":false,"capInsets":[0,0,0,0],"vertices":{"rawPosition":[],"indexes":[],"uv":[],"nuv":[],"minPos":{"x":0,"y":0,"z":0},"maxPos":{"x":0,"y":0,"z":0}},"packable":true,"pixelsToUnit":100,"pivot":{"x":0.5,"y":0.5},"meshType":0}],[0],0,[0],[0],[0]],[[{"name":"没牛02","rect":{"x":1585,"y":73,"width":196,"height":46},"offset":{"x":0,"y":-34},"originalSize":{"width":196,"height":114},"rotated":false,"capInsets":[0,0,0,0],"vertices":{"rawPosition":[],"indexes":[],"uv":[],"nuv":[],"minPos":{"x":0,"y":0,"z":0},"maxPos":{"x":0,"y":0,"z":0}},"packable":true,"pixelsToUnit":100,"pivot":{"x":0.5,"y":0.5},"meshType":0}],[0],0,[0],[0],[0]],[[{"name":"没牛03","rect":{"x":1585,"y":1,"width":196,"height":70},"offset":{"x":0,"y":-22},"originalSize":{"width":196,"height":114},"rotated":false,"capInsets":[0,0,0,0],"vertices":{"rawPosition":[],"indexes":[],"uv":[],"nuv":[],"minPos":{"x":0,"y":0,"z":0},"maxPos":{"x":0,"y":0,"z":0}},"packable":true,"pixelsToUnit":100,"pivot":{"x":0.5,"y":0.5},"meshType":0}],[0],0,[0],[0],[0]],[[{"name":"没牛08","rect":{"x":595,"y":1,"width":196,"height":112},"offset":{"x":0,"y":-1},"originalSize":{"width":196,"height":114},"rotated":false,"capInsets":[0,0,0,0],"vertices":{"rawPosition":[],"indexes":[],"uv":[],"nuv":[],"minPos":{"x":0,"y":0,"z":0},"maxPos":{"x":0,"y":0,"z":0}},"packable":true,"pixelsToUnit":100,"pivot":{"x":0.5,"y":0.5},"meshType":0}],[0],0,[0],[0],[0]],[[{"name":"没牛07","rect":{"x":199,"y":1,"width":196,"height":114},"offset":{"x":0,"y":0},"originalSize":{"width":196,"height":114},"rotated":false,"capInsets":[0,0,0,0],"vertices":{"rawPosition":[],"indexes":[],"uv":[],"nuv":[],"minPos":{"x":0,"y":0,"z":0},"maxPos":{"x":0,"y":0,"z":0}},"packable":true,"pixelsToUnit":100,"pivot":{"x":0.5,"y":0.5},"meshType":0}],[0],0,[0],[0],[0]],[[{"name":"没牛09","rect":{"x":1189,"y":1,"width":196,"height":108},"offset":{"x":0,"y":-3},"originalSize":{"width":196,"height":114},"rotated":false,"capInsets":[0,0,0,0],"vertices":{"rawPosition":[],"indexes":[],"uv":[],"nuv":[],"minPos":{"x":0,"y":0,"z":0},"maxPos":{"x":0,"y":0,"z":0}},"packable":true,"pixelsToUnit":100,"pivot":{"x":0.5,"y":0.5},"meshType":0}],[0],0,[0],[0],[0]],[[{"name":"没牛10","rect":{"x":991,"y":1,"width":196,"height":110},"offset":{"x":0,"y":-2},"originalSize":{"width":196,"height":114},"rotated":false,"capInsets":[0,0,0,0],"vertices":{"rawPosition":[],"indexes":[],"uv":[],"nuv":[],"minPos":{"x":0,"y":0,"z":0},"maxPos":{"x":0,"y":0,"z":0}},"packable":true,"pixelsToUnit":100,"pivot":{"x":0.5,"y":0.5},"meshType":0}],[0],0,[0],[0],[0]],[[{"name":"没牛00","rect":{"x":397,"y":115,"width":3,"height":3},"offset":{"x":-96.5,"y":55.5},"originalSize":{"width":196,"height":114},"rotated":false,"capInsets":[0,0,0,0],"vertices":{"rawPosition":[],"indexes":[],"uv":[],"nuv":[],"minPos":{"x":0,"y":0,"z":0},"maxPos":{"x":0,"y":0,"z":0}},"packable":true,"pixelsToUnit":100,"pivot":{"x":0.5,"y":0.5},"meshType":0}],[0],0,[0],[0],[0]],[[{"name":"没牛11","rect":{"x":793,"y":1,"width":196,"height":112},"offset":{"x":0,"y":-1},"originalSize":{"width":196,"height":114},"rotated":false,"capInsets":[0,0,0,0],"vertices":{"rawPosition":[],"indexes":[],"uv":[],"nuv":[],"minPos":{"x":0,"y":0,"z":0},"maxPos":{"x":0,"y":0,"z":0}},"packable":true,"pixelsToUnit":100,"pivot":{"x":0.5,"y":0.5},"meshType":0}],[0],0,[0],[0],[0]]]]
