[1,["94/aYpPw5PS4xj7yc+xyBV@6c48a"],["_textureSource"],["cc.SpriteFrame","cc.SpriteAtlas"],0,[[[{"name":"info_message_text","spriteFrames":["info_1","9bzJLn0l1Az5992dg4b1PR@91e19","info_2","9bzJLn0l1Az5992dg4b1PR@0eae4","info_3","9bzJLn0l1Az5992dg4b1PR@d2f16","info_4","9bzJLn0l1Az5992dg4b1PR@21a7c","info_5","9bzJLn0l1Az5992dg4b1PR@41eb8","info_6","9bzJLn0l1Az5992dg4b1PR@13b52","info_7","9bzJLn0l1Az5992dg4b1PR@058c7","info_tw","9bzJLn0l1Az5992dg4b1PR@ad134","info_win","9bzJLn0l1Az5992dg4b1PR@74bf6"]}],[1],0,[],[],[]],[[{"name":"info_7","rect":{"x":1,"y":904,"width":415,"height":43},"offset":{"x":0,"y":2},"originalSize":{"width":423,"height":49},"rotated":true,"capInsets":[0,0,0,0],"vertices":{"rawPosition":[],"indexes":[],"uv":[],"nuv":[],"minPos":{"x":0,"y":0,"z":0},"maxPos":{"x":0,"y":0,"z":0}},"packable":true,"pixelsToUnit":100,"pivot":{"x":0.5,"y":0.5},"meshType":0}],[0],0,[0],[0],[0]],[[{"name":"info_2","rect":{"x":46,"y":904,"width":366,"height":39},"offset":{"x":-1,"y":3},"originalSize":{"width":368,"height":49},"rotated":true,"capInsets":[0,0,0,0],"vertices":{"rawPosition":[],"indexes":[],"uv":[],"nuv":[],"minPos":{"x":0,"y":0,"z":0},"maxPos":{"x":0,"y":0,"z":0}},"packable":true,"pixelsToUnit":100,"pivot":{"x":0.5,"y":0.5},"meshType":0}],[0],0,[0],[0],[0]],[[{"name":"info_6","rect":{"x":1,"y":1321,"width":215,"height":43},"offset":{"x":-3,"y":1},"originalSize":{"width":221,"height":49},"rotated":true,"capInsets":[0,0,0,0],"vertices":{"rawPosition":[],"indexes":[],"uv":[],"nuv":[],"minPos":{"x":0,"y":0,"z":0},"maxPos":{"x":0,"y":0,"z":0}},"packable":true,"pixelsToUnit":100,"pivot":{"x":0.5,"y":0.5},"meshType":0}],[0],0,[0],[0],[0]],[[{"name":"info_4","rect":{"x":1,"y":1,"width":901,"height":35},"offset":{"x":-1,"y":1},"originalSize":{"width":903,"height":49},"rotated":true,"capInsets":[0,0,0,0],"vertices":{"rawPosition":[],"indexes":[],"uv":[],"nuv":[],"minPos":{"x":0,"y":0,"z":0},"maxPos":{"x":0,"y":0,"z":0}},"packable":true,"pixelsToUnit":100,"pivot":{"x":0.5,"y":0.5},"meshType":0}],[0],0,[0],[0],[0]],[[{"name":"info_5","rect":{"x":38,"y":1,"width":901,"height":35},"offset":{"x":-1,"y":1},"originalSize":{"width":903,"height":49},"rotated":true,"capInsets":[0,0,0,0],"vertices":{"rawPosition":[],"indexes":[],"uv":[],"nuv":[],"minPos":{"x":0,"y":0,"z":0},"maxPos":{"x":0,"y":0,"z":0}},"packable":true,"pixelsToUnit":100,"pivot":{"x":0.5,"y":0.5},"meshType":0}],[0],0,[0],[0],[0]],[[{"name":"info_win","rect":{"x":46,"y":1272,"width":116,"height":37},"offset":{"x":0,"y":1},"originalSize":{"width":118,"height":49},"rotated":true,"capInsets":[0,0,0,0],"vertices":{"rawPosition":[],"indexes":[],"uv":[],"nuv":[],"minPos":{"x":0,"y":0,"z":0},"maxPos":{"x":0,"y":0,"z":0}},"packable":true,"pixelsToUnit":100,"pivot":{"x":0.5,"y":0.5},"meshType":0}],[0],0,[0],[0],[0]],[[{"name":"info_1","rect":{"x":75,"y":1,"width":703,"height":43},"offset":{"x":0,"y":1},"originalSize":{"width":711,"height":49},"rotated":true,"capInsets":[0,0,0,0],"vertices":{"rawPosition":[],"indexes":[],"uv":[],"nuv":[],"minPos":{"x":0,"y":0,"z":0},"maxPos":{"x":0,"y":0,"z":0}},"packable":true,"pixelsToUnit":100,"pivot":{"x":0.5,"y":0.5},"meshType":0}],[0],0,[0],[0],[0]],[[{"name":"info_tw","rect":{"x":46,"y":1400,"width":104,"height":49},"offset":{"x":1,"y":0},"originalSize":{"width":106,"height":49},"rotated":true,"capInsets":[0,0,0,0],"vertices":{"rawPosition":[],"indexes":[],"uv":[],"nuv":[],"minPos":{"x":0,"y":0,"z":0},"maxPos":{"x":0,"y":0,"z":0}},"packable":true,"pixelsToUnit":100,"pivot":{"x":0.5,"y":0.5},"meshType":0}],[0],0,[0],[0],[0]],[[{"name":"info_3","rect":{"x":87,"y":706,"width":692,"height":35},"offset":{"x":1,"y":1},"originalSize":{"width":700,"height":49},"rotated":true,"capInsets":[0,0,0,0],"vertices":{"rawPosition":[],"indexes":[],"uv":[],"nuv":[],"minPos":{"x":0,"y":0,"z":0},"maxPos":{"x":0,"y":0,"z":0}},"packable":true,"pixelsToUnit":100,"pivot":{"x":0.5,"y":0.5},"meshType":0}],[0],0,[0],[0],[0]]]]
