[1,["f95650d1-a631-4fbe-9a16-0f1467901711@6c48a"],["_textureSource"],["cc.SpriteAtlas","cc.SpriteFrame"],0,[[[{"name":"1c35103b-7399-4e12-b83e-0b0a53363cb3.8eda2","spriteFrames":["respin_vfx_s_add","7015887b-f8c4-4df9-bee4-488a6f5e4e32@7c6f7"]}],[0],0,[],[],[]],[[{"name":"respin_vfx_s_add","rect":{"x":0,"y":0,"width":301,"height":446},"offset":{"x":0,"y":0},"originalSize":{"width":301,"height":446},"rotated":false,"capInsets":[0,0,0,0],"vertices":{"rawPosition":[],"indexes":[],"uv":[],"nuv":[],"minPos":{"x":0,"y":0,"z":0},"maxPos":{"x":0,"y":0,"z":0}},"packable":true,"pixelsToUnit":100,"pivot":{"x":0.5,"y":0.5},"meshType":0}],[1],0,[0],[0],[0]]]]
