[1,["94db3233-bbc5-4c12-b3d6-f6fd381fc580@6c48a"],["_textureSource"],["cc.SpriteFrame","cc.SpriteAtlas"],0,[[[{"name":"infoboard_win_text","spriteFrames":["info_tw","4f2554fb-7839-489b-b4b9-4b870e571583@ad134","info_win","4f2554fb-7839-489b-b4b9-4b870e571583@74bf6"]}],[1],0,[],[],[]],[[{"name":"info_win","rect":{"x":1,"y":78,"width":136,"height":47},"offset":{"x":1,"y":3},"originalSize":{"width":150,"height":81},"rotated":false,"capInsets":[0,0,0,0],"vertices":{"rawPosition":[],"indexes":[],"uv":[],"nuv":[],"minPos":{"x":0,"y":0,"z":0},"maxPos":{"x":0,"y":0,"z":0}},"packable":true,"pixelsToUnit":100,"pivot":{"x":0.5,"y":0.5},"meshType":0}],[0],0,[0],[0],[0]],[[{"name":"info_tw","rect":{"x":1,"y":1,"width":140,"height":75},"offset":{"x":0,"y":1},"originalSize":{"width":144,"height":81},"rotated":false,"capInsets":[0,0,0,0],"vertices":{"rawPosition":[],"indexes":[],"uv":[],"nuv":[],"minPos":{"x":0,"y":0,"z":0},"maxPos":{"x":0,"y":0,"z":0}},"packable":true,"pixelsToUnit":100,"pivot":{"x":0.5,"y":0.5},"meshType":0}],[0],0,[0],[0],[0]]]]
