[1,["6636bda9-e116-464a-99aa-08818c6bd49b@6c48a"],["_textureSource"],["cc.SpriteAtlas","cc.SpriteFrame"],0,[[[{"name":"d0a82d39-bede-46c4-b698-c81ff0dedfff.841f5","spriteFrames":["atom","f3f02648-b4a9-404b-bc74-f876157e93a8@3c0a6"]}],[0],0,[],[],[]],[[{"name":"atom","rect":{"x":0,"y":0,"width":31,"height":31},"offset":{"x":0,"y":0},"originalSize":{"width":31,"height":31},"rotated":false,"capInsets":[0,0,0,0],"vertices":{"rawPosition":[],"indexes":[],"uv":[],"nuv":[],"minPos":{"x":0,"y":0,"z":0},"maxPos":{"x":0,"y":0,"z":0}},"packable":true,"pixelsToUnit":100,"pivot":{"x":0.5,"y":0.5},"meshType":0}],[1],0,[0],[0],[0]]]]
