[1,["9dc03480-d1b6-4bb6-abf8-025fafd828c7@6c48a"],["_textureSource"],["cc.SpriteFrame","cc.SpriteAtlas"],0,[[[{"name":"big_win_text","spriteFrames":["big_win_text","d5b2226b-e8e5-4893-9b4f-3859142c3b69@181ba","bw","d5b2226b-e8e5-4893-9b4f-3859142c3b69@8b08c","mw","d5b2226b-e8e5-4893-9b4f-3859142c3b69@319c0","smw","d5b2226b-e8e5-4893-9b4f-3859142c3b69@9316e"]}],[1],0,[],[],[]],[[{"name":"big_win_text","rect":{"x":3,"y":2,"width":1664,"height":272},"offset":{"x":0,"y":0},"originalSize":{"width":1670,"height":276},"rotated":false,"capInsets":[0,0,0,0],"vertices":{"rawPosition":[],"indexes":[],"uv":[],"nuv":[],"minPos":{"x":0,"y":0,"z":0},"maxPos":{"x":0,"y":0,"z":0}},"packable":true,"pixelsToUnit":100,"pivot":{"x":0.5,"y":0.5},"meshType":0}],[0],0,[0],[0],[0]],[[{"name":"mw","rect":{"x":1201,"y":1,"width":468,"height":274},"offset":{"x":0,"y":0},"originalSize":{"width":468,"height":274},"rotated":false,"capInsets":[0,0,0,0],"vertices":{"rawPosition":[],"indexes":[],"uv":[],"nuv":[],"minPos":{"x":0,"y":0,"z":0},"maxPos":{"x":0,"y":0,"z":0}},"packable":true,"pixelsToUnit":100,"pivot":{"x":0.5,"y":0.5},"meshType":0}],[0],0,[0],[0],[0]],[[{"name":"bw","rect":{"x":711,"y":1,"width":488,"height":271},"offset":{"x":0,"y":0},"originalSize":{"width":488,"height":271},"rotated":false,"capInsets":[0,0,0,0],"vertices":{"rawPosition":[],"indexes":[],"uv":[],"nuv":[],"minPos":{"x":0,"y":0,"z":0},"maxPos":{"x":0,"y":0,"z":0}},"packable":true,"pixelsToUnit":100,"pivot":{"x":0.5,"y":0.5},"meshType":0}],[0],0,[0],[0],[0]],[[{"name":"smw","rect":{"x":1,"y":1,"width":708,"height":270},"offset":{"x":0,"y":0},"originalSize":{"width":708,"height":270},"rotated":false,"capInsets":[0,0,0,0],"vertices":{"rawPosition":[],"indexes":[],"uv":[],"nuv":[],"minPos":{"x":0,"y":0,"z":0},"maxPos":{"x":0,"y":0,"z":0}},"packable":true,"pixelsToUnit":100,"pivot":{"x":0.5,"y":0.5},"meshType":0}],[0],0,[0],[0],[0]]]]
