[1,["1634b62c3@6c48a"],["_textureSource"],["cc.SpriteFrame"],0,[[[{"name":"LINE","rect":{"x":3,"y":500,"width":500,"height":100},"offset":{"x":0,"y":0},"originalSize":{"width":500,"height":100},"rotated":true,"capInsets":[100,0,100,0],"packable":true,"pixelsToUnit":100,"pivot":{"x":0.5,"y":0.5},"meshType":0}],[0],0,[0],[0],[0]],[[{"name":"幸运时间标题bg","rect":{"x":3,"y":313,"width":920,"height":180},"offset":{"x":0,"y":0.5},"originalSize":{"width":920,"height":181},"rotated":false,"capInsets":[0,0,0,0],"packable":true,"pixelsToUnit":100,"pivot":{"x":0.5,"y":0.5},"meshType":0}],[0],0,[0],[0],[0]],[[{"name":"结算15","rect":{"x":208,"y":500,"width":479,"height":156},"offset":{"x":0,"y":0},"originalSize":{"width":479,"height":156},"rotated":true,"capInsets":[0,0,0,0],"packable":true,"pixelsToUnit":100,"pivot":{"x":0.5,"y":0.5},"meshType":0}],[0],0,[0],[0],[0]],[[{"name":"win","rect":{"x":890,"y":765,"width":249,"height":111},"offset":{"x":-3,"y":2},"originalSize":{"width":269,"height":201},"rotated":true,"capInsets":[0,0,0,0],"packable":true,"pixelsToUnit":100,"pivot":{"x":0.5,"y":0.5},"meshType":0}],[0],0,[0],[0],[0]],[[{"name":"开始按钮","rect":{"x":370,"y":765,"width":254,"height":255},"offset":{"x":0,"y":0.5},"originalSize":{"width":256,"height":258},"rotated":false,"capInsets":[0,0,0,0],"packable":true,"pixelsToUnit":100,"pivot":{"x":0.5,"y":0.5},"meshType":0}],[0],0,[0],[0],[0]],[[{"name":"progress_bar1","rect":{"x":975,"y":3,"width":420,"height":25},"offset":{"x":0,"y":0},"originalSize":{"width":420,"height":25},"rotated":true,"capInsets":[0,0,0,0],"packable":true,"pixelsToUnit":100,"pivot":{"x":0.5,"y":0.5},"meshType":0}],[0],0,[0],[0],[0]],[[{"name":"x10","rect":{"x":370,"y":499,"width":524,"height":260},"offset":{"x":0.5,"y":-0.5},"originalSize":{"width":525,"height":261},"rotated":false,"capInsets":[0,0,0,0],"packable":true,"pixelsToUnit":100,"pivot":{"x":0.5,"y":0.5},"meshType":0}],[0],0,[0],[0],[0]],[[{"name":"btn_exit","rect":{"x":900,"y":694,"width":75,"height":65},"offset":{"x":3.5,"y":0},"originalSize":{"width":88,"height":71},"rotated":false,"capInsets":[0,0,0,0],"packable":true,"pixelsToUnit":100,"pivot":{"x":0.5,"y":0.5},"meshType":0}],[0],0,[0],[0],[0]],[[{"name":"视频关","rect":{"x":929,"y":429,"width":90,"height":65},"offset":{"x":0,"y":0},"originalSize":{"width":90,"height":65},"rotated":false,"capInsets":[0,0,0,0],"packable":true,"pixelsToUnit":100,"pivot":{"x":0.5,"y":0.5},"meshType":0}],[0],0,[0],[0],[0]],[[{"name":"结算8","rect":{"x":3,"y":3,"width":966,"height":304},"offset":{"x":0,"y":0},"originalSize":{"width":966,"height":306},"rotated":false,"capInsets":[0,0,0,0],"packable":true,"pixelsToUnit":100,"pivot":{"x":0.5,"y":0.5},"meshType":0}],[0],0,[0],[0],[0]],[[{"name":"按钮叶子2","rect":{"x":900,"y":500,"width":111,"height":83},"offset":{"x":0,"y":0},"originalSize":{"width":111,"height":83},"rotated":false,"capInsets":[0,0,0,0],"packable":true,"pixelsToUnit":100,"pivot":{"x":0.5,"y":0.5},"meshType":0}],[0],0,[0],[0],[0]],[[{"name":"刷新","rect":{"x":900,"y":589,"width":99,"height":100},"offset":{"x":0,"y":0},"originalSize":{"width":99,"height":100},"rotated":true,"capInsets":[0,0,0,0],"packable":true,"pixelsToUnit":100,"pivot":{"x":0.5,"y":0.5},"meshType":0}],[0],0,[0],[0],[0]],[[{"name":"天秤","rect":{"x":630,"y":765,"width":254,"height":254},"offset":{"x":0,"y":0},"originalSize":{"width":254,"height":254},"rotated":false,"capInsets":[0,0,0,0],"packable":true,"pixelsToUnit":100,"pivot":{"x":0.5,"y":0.5},"meshType":0}],[0],0,[0],[0],[0]],[[{"name":"bg_common_mask","rect":{"x":109,"y":500,"width":489,"height":93},"offset":{"x":1.5,"y":-84.5},"originalSize":{"width":500,"height":500},"rotated":true,"capInsets":[0,0,0,0],"packable":true,"pixelsToUnit":100,"pivot":{"x":0.5,"y":0.5},"meshType":0}],[0],0,[0],[0],[0]]]]
