[1,["47AEBoSM1KjaplkOoQiUt9@f9941","7aBxbhDOpDqaSgMGE+6cNn@f9941","e6sQg4OuVEjpvBKaR5B+1i@f9941","45rEhgvkNIRKNnYu12ICw4@f9941","ecWgFQ5XNHSIgkl6w8+cIm@f9941","73L5tKeEBL554dYULDph2E@f9941","7bOxDZfNNFype2KWjWi4ji@f9941","balKJrb1hPfZHICFa8Vf3d@f9941","6e3OunpvlCnK7CP1JMiz6c@f9941","4fL3zOvR5PaL+9fXEW3s84@f9941","35DmmUxNtMGat5cjOcPy5u@f9941","68vhJx+GNFcrcX2Yyd8thW@f9941","acal9ADzVPF6fQXQG2U8/P@f9941","35DmmUxNtMGat5cjOcPy5u@6c48a","45rEhgvkNIRKNnYu12ICw4@6c48a","47AEBoSM1KjaplkOoQiUt9@6c48a","4fL3zOvR5PaL+9fXEW3s84@6c48a","68vhJx+GNFcrcX2Yyd8thW@6c48a","6e3OunpvlCnK7CP1JMiz6c@6c48a","73L5tKeEBL554dYULDph2E@6c48a","7aBxbhDOpDqaSgMGE+6cNn@6c48a","7bOxDZfNNFype2KWjWi4ji@6c48a","acal9ADzVPF6fQXQG2U8/P@6c48a","balKJrb1hPfZHICFa8Vf3d@6c48a","e6sQg4OuVEjpvBKaR5B+1i@6c48a","ecWgFQ5XNHSIgkl6w8+cIm@6c48a"],["node","_spriteFrame","_textureSource","root","data"],["cc.SpriteFrame",["cc.Node",["_name","_layer","_active","_components","_prefab","_parent","_children","_lpos"],0,9,4,1,2,5],["cc.Prefab",["_name"],2],["cc.UITransform",["node","__prefab","_contentSize"],3,1,4,5],["cc.CompPrefabInfo",["fileId"],2],["40e67jvbiNBNZhqs52pa0qJ",["node","__prefab"],3,1,4],["cc.CircleCollider2D",["_group","_sensor","_friction","_radius","node","__prefab","_offset"],-1,1,4,5],["cc.RigidBody2D",["enabledContactListener","_group","_allowSleep","_gravityScale","node","__prefab"],-1,1,4],["cc.PrefabInfo",["fileId","instance","targetOverrides","nestedPrefabInstanceRoots","root","asset"],-1,1,1],["cc.Sprite",["node","__prefab","_spriteFrame"],3,1,4,6]],[[4,0,2],[3,0,1,2,1],[8,0,1,2,3,4,5,5],[9,0,1,2,1],[1,0,2,1,5,3,4,4],[2,0,2],[1,0,1,6,3,4,3],[1,0,1,5,3,4,3],[1,0,2,1,5,3,4,7,4],[5,0,1,1],[6,0,1,2,3,4,5,6,5],[7,0,1,2,3,4,5,5]],[[[[5,"bullet"],[6,"bullet",33554432,[-6,-7,-8,-9,-10,-11,-12,-13,-14,-15,-16,-17,-18],[[1,-2,[0,"dfQQItovZL7aSZE7eZfqOW"],[5,0,0]],[9,-3,[0,"370IAd2/9NI7tpP2nehr1q"]],[10,8,true,0,13.8,-4,[0,"d7r3+0Dr1IWbCzVfTSv/F7"],[0,0,30]],[11,true,8,false,0,-5,[0,"2btDUCcjZDsId97DH0XBxt"]]],[2,"e4MbDGSBNMgrG4L6M7CivA",null,null,null,-1,0]],[7,"1",33554432,1,[[1,-19,[0,"95AMkW5gRECIgdc5TisseD"],[5,52,117]],[3,-20,[0,"ffjDK9IuhL/r6l2FUWl67K"],0]],[2,"77kkt+HJpAXZQt5rOobhsf",null,null,null,1,0]],[4,"2",false,33554432,1,[[1,-21,[0,"09S9UIphtM66LslYeCHH8H"],[5,52,117]],[3,-22,[0,"72dRgJkfJBgZsjFDsalict"],1]],[2,"da1Np5HydL2IHxsxfZjY0J",null,null,null,1,0]],[4,"3",false,33554432,1,[[1,-23,[0,"4fdeaLlnRPrbqrjIkLZYxg"],[5,52,117]],[3,-24,[0,"fboNGizHpL8LtYdTmTMS0a"],2]],[2,"81Iwe9cFdIPIpOn2JB+DtM",null,null,null,1,0]],[4,"4",false,33554432,1,[[1,-25,[0,"d6TUUiaHhAW5T7J6Q9+TTH"],[5,52,117]],[3,-26,[0,"97yR9D3c5NhJOpKPSbKM/3"],3]],[2,"58h6vzmm1MYortBC2fI4OL",null,null,null,1,0]],[4,"5",false,33554432,1,[[1,-27,[0,"8bbHIoOotJjpM/kf272fsg"],[5,101,97]],[3,-28,[0,"f4AMd3qnpE67ft+Iim/bb6"],4]],[2,"93yW4U/GVJ/JEY9jvtdMNI",null,null,null,1,0]],[4,"6",false,33554432,1,[[1,-29,[0,"aeCBCKlHxITrh9HMmEReAX"],[5,101,97]],[3,-30,[0,"085D5k+xpPFqRPHhN9Nc7y"],5]],[2,"a8NDQRgxRGVKGk47o/gGY9",null,null,null,1,0]],[4,"7",false,33554432,1,[[1,-31,[0,"20CA+y/iBKUryQSFOMSXol"],[5,101,97]],[3,-32,[0,"b7pQDE57dLD50TAQxL1qHJ"],6]],[2,"feP57nPRBBKqRUUG2lKFX/",null,null,null,1,0]],[4,"8",false,33554432,1,[[1,-33,[0,"23Ao/7cPtLgaRnb3ujNEU9"],[5,101,97]],[3,-34,[0,"04W8z5A1dGtLokEDXAu0NU"],7]],[2,"feWlbRDr1P96lD5/rcOmei",null,null,null,1,0]],[4,"9",false,33554432,1,[[1,-35,[0,"5akzLfBi1BD6IGmWiYooI7"],[5,129,129]],[3,-36,[0,"ffHKoozQVMwKf7lj4w+lNZ"],8]],[2,"0eyuUQIPlBuKSpbsrt0VlR",null,null,null,1,0]],[4,"10",false,33554432,1,[[1,-37,[0,"76dmaf1GZFDZVp4BTV6w3k"],[5,129,129]],[3,-38,[0,"651QSI4j9InZbrWluvk2Cv"],9]],[2,"decJaybrhF35s/NEj3HC+T",null,null,null,1,0]],[4,"11",false,33554432,1,[[1,-39,[0,"e0iy90/6xBxpo/cxZ8WWh7"],[5,129,129]],[3,-40,[0,"0f4FxCcK1LwL/r8bL+GWbF"],10]],[2,"9fiAeyuvVJTptU1yrtD4fq",null,null,null,1,0]],[4,"12",false,33554432,1,[[1,-41,[0,"adTp9K9nNNS73/QViDq3Ov"],[5,129,129]],[3,-42,[0,"e6eJp4QY5JmLpTmKFuKqyj"],11]],[2,"562b1/nmJFfJBBkMdb7LeM",null,null,null,1,0]],[8,"13",false,33554432,1,[[1,-43,[0,"03ami3uS9KGLoYUKySbw+Z"],[5,163,202]],[3,-44,[0,"1021Yv2KBOy62LNZQp+voL"],12]],[2,"caieU26YxPNpKdS5QqVnd8",null,null,null,1,0],[1,0,-17.097,0]]],0,[0,3,1,0,0,1,0,0,1,0,0,1,0,0,1,0,-1,2,0,-2,3,0,-3,4,0,-4,5,0,-5,6,0,-6,7,0,-7,8,0,-8,9,0,-9,10,0,-10,11,0,-11,12,0,-12,13,0,-13,14,0,0,2,0,0,2,0,0,3,0,0,3,0,0,4,0,0,4,0,0,5,0,0,5,0,0,6,0,0,6,0,0,7,0,0,7,0,0,8,0,0,8,0,0,9,0,0,9,0,0,10,0,0,10,0,0,11,0,0,11,0,0,12,0,0,12,0,0,13,0,0,13,0,0,14,0,0,14,0,4,1,44],[0,0,0,0,0,0,0,0,0,0,0,0,0],[1,1,1,1,1,1,1,1,1,1,1,1,1],[0,1,2,3,4,5,6,7,8,9,10,11,12]],[[{"name":"Zidan_3_3","rect":{"x":0,"y":0,"width":129,"height":129},"offset":{"x":0,"y":0},"originalSize":{"width":129,"height":129},"rotated":false,"capInsets":[0,0,0,0],"vertices":{"rawPosition":[-64.5,-64.5,0,64.5,-64.5,0,-64.5,64.5,0,64.5,64.5,0],"indexes":[0,1,2,2,1,3],"uv":[0,129,129,129,0,0,129,0],"nuv":[0,0,1,0,0,1,1,1],"minPos":{"x":-64.5,"y":-64.5,"z":0},"maxPos":{"x":64.5,"y":64.5,"z":0}},"packable":true,"pixelsToUnit":100,"pivot":{"x":0.5,"y":0.5},"meshType":0}],[0],0,[0],[2],[13]],[[{"name":"Zidan_1_4","rect":{"x":0,"y":0,"width":52,"height":117},"offset":{"x":0,"y":0},"originalSize":{"width":52,"height":117},"rotated":false,"capInsets":[0,0,0,0],"vertices":{"rawPosition":[-26,-58.5,0,26,-58.5,0,-26,58.5,0,26,58.5,0],"indexes":[0,1,2,2,1,3],"uv":[0,117,52,117,0,0,52,0],"nuv":[0,0,1,0,0,1,1,1],"minPos":{"x":-26,"y":-58.5,"z":0},"maxPos":{"x":26,"y":58.5,"z":0}},"packable":true,"pixelsToUnit":100,"pivot":{"x":0.5,"y":0.5},"meshType":0}],[0],0,[0],[2],[14]],[[{"name":"Zidan_1_1","rect":{"x":0,"y":0,"width":52,"height":117},"offset":{"x":0,"y":0},"originalSize":{"width":52,"height":117},"rotated":false,"capInsets":[0,0,0,0],"vertices":{"rawPosition":[-26,-58.5,0,26,-58.5,0,-26,58.5,0,26,58.5,0],"indexes":[0,1,2,2,1,3],"uv":[0,117,52,117,0,0,52,0],"nuv":[0,0,1,0,0,1,1,1],"minPos":{"x":-26,"y":-58.5,"z":0},"maxPos":{"x":26,"y":58.5,"z":0}},"packable":true,"pixelsToUnit":100,"pivot":{"x":0.5,"y":0.5},"meshType":0}],[0],0,[0],[2],[15]],[[{"name":"Zidan_3_2","rect":{"x":0,"y":0,"width":129,"height":129},"offset":{"x":0,"y":0},"originalSize":{"width":129,"height":129},"rotated":false,"capInsets":[0,0,0,0],"vertices":{"rawPosition":[-64.5,-64.5,0,64.5,-64.5,0,-64.5,64.5,0,64.5,64.5,0],"indexes":[0,1,2,2,1,3],"uv":[0,129,129,129,0,0,129,0],"nuv":[0,0,1,0,0,1,1,1],"minPos":{"x":-64.5,"y":-64.5,"z":0},"maxPos":{"x":64.5,"y":64.5,"z":0}},"packable":true,"pixelsToUnit":100,"pivot":{"x":0.5,"y":0.5},"meshType":0}],[0],0,[0],[2],[16]],[[{"name":"Zidan_3_4","rect":{"x":0,"y":0,"width":129,"height":129},"offset":{"x":0,"y":0},"originalSize":{"width":129,"height":129},"rotated":false,"capInsets":[0,0,0,0],"vertices":{"rawPosition":[-64.5,-64.5,0,64.5,-64.5,0,-64.5,64.5,0,64.5,64.5,0],"indexes":[0,1,2,2,1,3],"uv":[0,129,129,129,0,0,129,0],"nuv":[0,0,1,0,0,1,1,1],"minPos":{"x":-64.5,"y":-64.5,"z":0},"maxPos":{"x":64.5,"y":64.5,"z":0}},"packable":true,"pixelsToUnit":100,"pivot":{"x":0.5,"y":0.5},"meshType":0}],[0],0,[0],[2],[17]],[[{"name":"Zidan_3_1","rect":{"x":0,"y":0,"width":129,"height":129},"offset":{"x":0,"y":0},"originalSize":{"width":129,"height":129},"rotated":false,"capInsets":[0,0,0,0],"vertices":{"rawPosition":[-64.5,-64.5,0,64.5,-64.5,0,-64.5,64.5,0,64.5,64.5,0],"indexes":[0,1,2,2,1,3],"uv":[0,129,129,129,0,0,129,0],"nuv":[0,0,1,0,0,1,1,1],"minPos":{"x":-64.5,"y":-64.5,"z":0},"maxPos":{"x":64.5,"y":64.5,"z":0}},"packable":true,"pixelsToUnit":100,"pivot":{"x":0.5,"y":0.5},"meshType":0}],[0],0,[0],[2],[18]],[[{"name":"Zidan_2_2","rect":{"x":0,"y":0,"width":101,"height":97},"offset":{"x":0,"y":0},"originalSize":{"width":101,"height":97},"rotated":false,"capInsets":[0,0,0,0],"vertices":{"rawPosition":[-50.5,-48.5,0,50.5,-48.5,0,-50.5,48.5,0,50.5,48.5,0],"indexes":[0,1,2,2,1,3],"uv":[0,97,101,97,0,0,101,0],"nuv":[0,0,1,0,0,1,1,1],"minPos":{"x":-50.5,"y":-48.5,"z":0},"maxPos":{"x":50.5,"y":48.5,"z":0}},"packable":true,"pixelsToUnit":100,"pivot":{"x":0.5,"y":0.5},"meshType":0}],[0],0,[0],[2],[19]],[[{"name":"Zidan_1_2","rect":{"x":0,"y":0,"width":52,"height":117},"offset":{"x":0,"y":0},"originalSize":{"width":52,"height":117},"rotated":false,"capInsets":[0,0,0,0],"vertices":{"rawPosition":[-26,-58.5,0,26,-58.5,0,-26,58.5,0,26,58.5,0],"indexes":[0,1,2,2,1,3],"uv":[0,117,52,117,0,0,52,0],"nuv":[0,0,1,0,0,1,1,1],"minPos":{"x":-26,"y":-58.5,"z":0},"maxPos":{"x":26,"y":58.5,"z":0}},"packable":true,"pixelsToUnit":100,"pivot":{"x":0.5,"y":0.5},"meshType":0}],[0],0,[0],[2],[20]],[[{"name":"Zidan_2_3","rect":{"x":0,"y":0,"width":101,"height":97},"offset":{"x":0,"y":0},"originalSize":{"width":101,"height":97},"rotated":false,"capInsets":[0,0,0,0],"vertices":{"rawPosition":[-50.5,-48.5,0,50.5,-48.5,0,-50.5,48.5,0,50.5,48.5,0],"indexes":[0,1,2,2,1,3],"uv":[0,97,101,97,0,0,101,0],"nuv":[0,0,1,0,0,1,1,1],"minPos":{"x":-50.5,"y":-48.5,"z":0},"maxPos":{"x":50.5,"y":48.5,"z":0}},"packable":true,"pixelsToUnit":100,"pivot":{"x":0.5,"y":0.5},"meshType":0}],[0],0,[0],[2],[21]],[[{"name":"Zidan_4_1","rect":{"x":0,"y":0,"width":163,"height":202},"offset":{"x":0,"y":0},"originalSize":{"width":163,"height":202},"rotated":false,"capInsets":[0,0,0,0],"vertices":{"rawPosition":[-81.5,-101,0,81.5,-101,0,-81.5,101,0,81.5,101,0],"indexes":[0,1,2,2,1,3],"uv":[0,202,163,202,0,0,163,0],"nuv":[0,0,1,0,0,1,1,1],"minPos":{"x":-81.5,"y":-101,"z":0},"maxPos":{"x":81.5,"y":101,"z":0}},"packable":true,"pixelsToUnit":100,"pivot":{"x":0.5,"y":0.5},"meshType":0}],[0],0,[0],[2],[22]],[[{"name":"Zidan_2_4","rect":{"x":0,"y":0,"width":101,"height":97},"offset":{"x":0,"y":0},"originalSize":{"width":101,"height":97},"rotated":false,"capInsets":[0,0,0,0],"vertices":{"rawPosition":[-50.5,-48.5,0,50.5,-48.5,0,-50.5,48.5,0,50.5,48.5,0],"indexes":[0,1,2,2,1,3],"uv":[0,97,101,97,0,0,101,0],"nuv":[0,0,1,0,0,1,1,1],"minPos":{"x":-50.5,"y":-48.5,"z":0},"maxPos":{"x":50.5,"y":48.5,"z":0}},"packable":true,"pixelsToUnit":100,"pivot":{"x":0.5,"y":0.5},"meshType":0}],[0],0,[0],[2],[23]],[[{"name":"Zidan_1_3","rect":{"x":0,"y":0,"width":52,"height":117},"offset":{"x":0,"y":0},"originalSize":{"width":52,"height":117},"rotated":false,"capInsets":[0,0,0,0],"vertices":{"rawPosition":[-26,-58.5,0,26,-58.5,0,-26,58.5,0,26,58.5,0],"indexes":[0,1,2,2,1,3],"uv":[0,117,52,117,0,0,52,0],"nuv":[0,0,1,0,0,1,1,1],"minPos":{"x":-26,"y":-58.5,"z":0},"maxPos":{"x":26,"y":58.5,"z":0}},"packable":true,"pixelsToUnit":100,"pivot":{"x":0.5,"y":0.5},"meshType":0}],[0],0,[0],[2],[24]],[[{"name":"Zidan_2_1","rect":{"x":0,"y":0,"width":101,"height":97},"offset":{"x":0,"y":0},"originalSize":{"width":101,"height":97},"rotated":false,"capInsets":[0,0,0,0],"vertices":{"rawPosition":[-50.5,-48.5,0,50.5,-48.5,0,-50.5,48.5,0,50.5,48.5,0],"indexes":[0,1,2,2,1,3],"uv":[0,97,101,97,0,0,101,0],"nuv":[0,0,1,0,0,1,1,1],"minPos":{"x":-50.5,"y":-48.5,"z":0},"maxPos":{"x":50.5,"y":48.5,"z":0}},"packable":true,"pixelsToUnit":100,"pivot":{"x":0.5,"y":0.5},"meshType":0}],[0],0,[0],[2],[25]]]]
